LICENSE
MANIFEST.in
README.md
setup.cfg
setup.py
cppguts/__init__.py
cppguts/dumpcpp.py
cppguts/editcpp.py
cppguts.egg-info/PKG-INFO
cppguts.egg-info/SOURCES.txt
cppguts.egg-info/dependency_links.txt
cppguts.egg-info/entry_points.txt
cppguts.egg-info/requires.txt
cppguts.egg-info/top_level.txt
cppguts/tests/__init__.py
cppguts/tests/test_cppguts.py
cppguts/tests/data/dest.h.in
cppguts/tests/data/src.h.in