Metadata-Version: 2.1
Name: cppguts
Version: 1.0.1
Summary: Tool aimed at C/C++ source code correction that allows to automatically find and copy/paste new function definition
Home-page: https://github.com/tierra-colada/cppguts
Author: kerim khemrev
Author-email: tierracolada@gmail.com
License: MIT
Download-URL: https://github.com/tierra-colada/cppguts/archive/refs/tags/v1.0.1.tar.gz
Keywords: c cpp c-parser cpp-parser c-editor cpp-editor c-generator cpp-generator
Platform: UNKNOWN
Classifier: Development Status :: 5 - Production/Stable
Classifier: Environment :: Console
Classifier: Intended Audience :: Developers
Classifier: Topic :: Software Development :: Build Tools
Classifier: Programming Language :: Python :: 3.6
Classifier: Topic :: Software Development :: Code Generators
Classifier: License :: OSI Approved :: MIT License
Classifier: Programming Language :: Python :: 3
Classifier: Programming Language :: Python :: 3.6
Classifier: Programming Language :: Python :: 3.7
Classifier: Programming Language :: Python :: 3.8
Classifier: Programming Language :: Python :: 3.9
Requires-Python: >=3
License-File: LICENSE
